[
  {
    "uuid": "2ea3c97a-dc9c-31d0-81a0-1b6efd4f886c",
    "name": "MrPers202",
    "level": 4,
    "bypassesPlayerLimit": false
  },
  {
    "uuid": "59002451-baa0-3fa2-8583-f79ce5faca96",
    "name": "ZPekena_Jenny_LK",
    "level": 4,
    "bypassesPlayerLimit": false
  },
  {
    "uuid": "c4894f17-3edf-37fe-9943-defe2e75885b",
    "name": "atiradorfgsa",
    "level": 4,
    "bypassesPlayerLimit": false
  },
  {
    "uuid": "e5ca2bd3-8916-332b-911d-438f6a098559",
    "name": "rukia",
    "level": 4,
    "bypassesPlayerLimit": false
  },
  {
    "uuid": "ea1f76d2-9e4d-3f54-af75-15eaebe11be2",
    "name": "Teste",
    "level": 4,
    "bypassesPlayerLimit": false
  },
  {
    "uuid": "ba7bec48-d927-3748-b727-e576eb91c6ac",
    "name": "craines",
    "level": 4,
    "bypassesPlayerLimit": false
  },
  {
    "uuid": "51665af8-609e-34f3-98c0-861b952962d1",
    "name": "imRoZz",
    "level": 4,
    "bypassesPlayerLimit": false
  },
  {
    "uuid": "5de5661c-30cb-329b-9ad2-3488c24855e3",
    "name": "kendall22",
    "level": 4,
    "bypassesPlayerLimit": false
  },
  {
    "uuid": "97007d09-6055-3091-85ae-800f82fc2bb2",
    "name": "juniorplaygame",
    "level": 4,
    "bypassesPlayerLimit": false
  },
  {
    "uuid": "f3a912d4-db2d-377a-9682-5a88e41f0c5d",
    "name": "dudanq",
    "level": 4,
    "bypassesPlayerLimit": false
  },
  {
    "uuid": "66406033-f81f-309d-bc6e-24fd42195503",
    "name": "TotalmenteGamer",
    "level": 4,
    "bypassesPlayerLimit": false
  },
  {
    "uuid": "97ddef75-cc5b-330d-9cd7-9f4127683c74",
    "name": "extreme_pvp_br",
    "level": 4,
    "bypassesPlayerLimit": false
  },
  {
    "uuid": "4fdf550e-f3b3-3a06-8485-0916b2b491bc",
    "name": "teste",
    "level": 4,
    "bypassesPlayerLimit": false
  },
  {
    "uuid": "b3d0390d-c374-3048-a078-f90d60a144f8",
    "name": "Rukia",
    "level": 4,
    "bypassesPlayerLimit": false
  }
]