{"stat.beaconInteraction":6,"stat.walkOneCm":113831,"achievement.openInventory":13,"stat.useItem.minecraft.stone":86,"stat.leaveGame":8,"stat.damageTaken":340,"stat.useItem.minecraft.tnt":1,"stat.useItem.minecraft.bucket":1280,"stat.flyOneCm":369512,"stat.deaths":1,"stat.jump":134,"stat.swimOneCm":37350,"stat.playOneMinute":154057,"stat.useItem.minecraft.planks":69,"stat.climbOneCm":1604,"stat.fallOneCm":967,"stat.damageDealt":15,"stat.crouchOneCm":946,"stat.timeSinceDeath":2196,"stat.sprintOneCm":9650,"achievement.exploreAllBiomes":{"value":0,"progress":["Ocean","Plains","TaigaHills"]},"stat.diveOneCm":12645}